<odoo>
  <data>
    <!-- explicit list view definition -->
<!--
    <record model="ir.ui.view" id="jst_lms_group.list">
      <field name="name">jst_lms_group list</field>
      <field name="model">jst_lms_group.jst_lms_group</field>
      <field name="arch" type="xml">
        <tree>
          <field name="name"/>
          <field name="value"/>
          <field name="value2"/>
        </tree>
      </field>
    </record>
-->

    <!-- actions opening views on models -->
<!--
    <record model="ir.actions.act_window" id="jst_lms_group.action_window">
      <field name="name">jst_lms_group window</field>
      <field name="res_model">jst_lms_group.jst_lms_group</field>
      <field name="view_mode">tree,form</field>
    </record>
-->

    <!-- server action to the one above -->
<!--
    <record model="ir.actions.server" id="jst_lms_group.action_server">
      <field name="name">jst_lms_group server</field>
      <field name="model_id" ref="model_jst_lms_group_jst_lms_group"/>
      <field name="state">code</field>
      <field name="code">
        action = {
          "type": "ir.actions.act_window",
          "view_mode": "tree,form",
          "res_model": model._name,
        }
      </field>
    </record>
-->

    <!-- Top menu item -->
<!--
    <menuitem name="jst_lms_group" id="jst_lms_group.menu_root"/>
-->
    <!-- menu categories -->
<!--
    <menuitem name="Menu 1" id="jst_lms_group.menu_1" parent="jst_lms_group.menu_root"/>
    <menuitem name="Menu 2" id="jst_lms_group.menu_2" parent="jst_lms_group.menu_root"/>
-->
    <!-- actions -->
<!--
    <menuitem name="List" id="jst_lms_group.menu_1_list" parent="jst_lms_group.menu_1"
              action="jst_lms_group.action_window"/>
    <menuitem name="Server to list" id="jst_lms_group" parent="jst_lms_group.menu_2"
              action="jst_lms_group.action_server"/>
-->
  </data>
</odoo>
